Metadata-Version: 1.1
Name: multiscale
Version: 1.0.1
Summary: Scale images from input directories to multiple resolution levels separated into multiple directories
Home-page: https://github.com/AttilaVM/multiscale
Author: Attila V. Molnar
Author-email: ate.molnar2@gmail.com
License: MIT
Keywords: scale image image-manipulation PythonMagick
Platform: UNKNOWN
Classifier: Environment :: Console
Classifier: Intended Audience :: Developers
Classifier: Programming Language :: Python :: 3.4
Classifier: Topic :: Multimedia :: Graphics
